esphomeyaml/__init__.py
esphomeyaml/__main__.py
esphomeyaml/automation.py
esphomeyaml/config.py
esphomeyaml/config_validation.py
esphomeyaml/const.py
esphomeyaml/core.py
esphomeyaml/espota.py
esphomeyaml/helpers.py
esphomeyaml/mqtt.py
esphomeyaml/pins.py
esphomeyaml/wizard.py
esphomeyaml/writer.py
esphomeyaml/yaml_util.py
esphomeyaml/components/__init__.py
esphomeyaml/components/ads1115.py
esphomeyaml/components/dallas.py
esphomeyaml/components/debug.py
esphomeyaml/components/deep_sleep.py
esphomeyaml/components/esp32_ble.py
esphomeyaml/components/esp32_touch.py
esphomeyaml/components/i2c.py
esphomeyaml/components/ir_transmitter.py
esphomeyaml/components/logger.py
esphomeyaml/components/mqtt.py
esphomeyaml/components/ota.py
esphomeyaml/components/pca9685.py
esphomeyaml/components/pcf8574.py
esphomeyaml/components/power_supply.py
esphomeyaml/components/web_server.py
esphomeyaml/components/wifi.py
esphomeyaml/components/binary_sensor/__init__.py
esphomeyaml/components/binary_sensor/esp32_ble.py
esphomeyaml/components/binary_sensor/esp32_touch.py
esphomeyaml/components/binary_sensor/gpio.py
esphomeyaml/components/binary_sensor/status.py
esphomeyaml/components/binary_sensor/template.py
esphomeyaml/components/cover/__init__.py
esphomeyaml/components/cover/template.py
esphomeyaml/components/fan/__init__.py
esphomeyaml/components/fan/binary.py
esphomeyaml/components/fan/speed.py
esphomeyaml/components/light/__init__.py
esphomeyaml/components/light/binary.py
esphomeyaml/components/light/fastled_clockless.py
esphomeyaml/components/light/fastled_spi.py
esphomeyaml/components/light/monochromatic.py
esphomeyaml/components/light/rgb.py
esphomeyaml/components/light/rgbw.py
esphomeyaml/components/output/__init__.py
esphomeyaml/components/output/esp8266_pwm.py
esphomeyaml/components/output/gpio.py
esphomeyaml/components/output/ledc.py
esphomeyaml/components/output/pca9685.py
esphomeyaml/components/sensor/__init__.py
esphomeyaml-1.6.1.dist-info/METADATA
esphomeyaml-1.6.1.dist-info/RECORD
esphomeyaml-1.6.1.dist-info/WHEEL
esphomeyaml-1.6.1.dist-info/entry_points.txt
esphomeyaml-1.6.1.dist-info/top_level.txt
