Metadata-Version: 2.1
Name: esphomeyaml
Version: 1.6.1
Summary: Make creating custom firmwares for ESP32/ESP8266 super easy.
Home-page: https://github.com/OttoWinter/esphomeyaml
Author: Otto Winter
Author-email: contact@otto-winter.com
License: MIT
Download-URL: https://github.com/OttoWinter/esphomeyaml/archive/1.6.1.zip
Keywords: home,automation
Platform: any
Requires-Python: >=2.7,<3
Requires-Dist: voluptuous (>=0.11.1)
Requires-Dist: platformio (>=3.5.2)
Requires-Dist: pyyaml (>=3.12)
Requires-Dist: paho-mqtt (>=1.3.1)
Requires-Dist: colorlog (>=3.1.2)
Requires-Dist: tornado (>=5.0.0)
Requires-Dist: esptool (>=2.3.1)
